pyJHTDB/__init__.py
pyjhtdb-20260124.2.dist-info/METADATA
pyjhtdb-20260124.2.dist-info/WHEEL
pyjhtdb-20260124.2.dist-info/top_level.txt
pyjhtdb-20260124.2.dist-info/RECORD
