Metadata-Version: 2.4
Name: pyJHTDB
Version: 20260124.2
Summary: DEPRECATED - Use giverny instead
Classifier: Programming Language :: Python :: 3
Classifier: Programming Language :: Python :: 3.9
Classifier: Programming Language :: Python :: 3.10
Classifier: Programming Language :: Python :: 3.11
Classifier: Programming Language :: Python :: 3.12
Requires-Python: >=3.9
